fsrl/__init__.py
fsrl/agent/__init__.py
fsrl/agent/base_agent.py
fsrl/agent/cpo_agent.py
fsrl/agent/cvpo_agent.py
fsrl/agent/ddpg_lag_agent.py
fsrl/agent/focops_agent.py
fsrl/agent/ppo_lag_agent.py
fsrl/agent/sac_lag_agent.py
fsrl/agent/trpo_lag_agent.py
fsrl/config/__init__.py
fsrl/config/cpo_cfg.py
fsrl/config/cvpo_cfg.py
fsrl/config/ddpgl_cfg.py
fsrl/config/focosp_cfg.py
fsrl/config/ppol_cfg.py
fsrl/config/sacl_cfg.py
fsrl/config/trpol_cfg.py
fsrl/data/__init__.py
fsrl/data/basic_collector.py
fsrl/data/fast_collector.py
fsrl/data/traj_buf.py
fsrl/policy/__init__.py
fsrl/policy/base_policy.py
fsrl/policy/cpo.py
fsrl/policy/cvpo.py
fsrl/policy/ddpg_lag.py
fsrl/policy/focops.py
fsrl/policy/lagrangian_base.py
fsrl/policy/ppo_lag.py
fsrl/policy/sac_lag.py
fsrl/policy/trpo_lag.py
fsrl/trainer/__init__.py
fsrl/trainer/base_trainer.py
fsrl/trainer/offpolicy.py
fsrl/trainer/onpolicy.py
fsrl/utils/__init__.py
fsrl/utils/exp_util.py
fsrl/utils/optim_util.py
fsrl/utils/logger/__init__.py
fsrl/utils/logger/base_logger.py
fsrl/utils/logger/logger_util.py
fsrl/utils/logger/tb_logger.py
fsrl/utils/logger/wandb_logger.py
fsrl/utils/net/__init__.py
fsrl/utils/net/common.py
fsrl/utils/net/continuous.py
fast_safe_rl-0.1.0.dist-info/LICENSE
fast_safe_rl-0.1.0.dist-info/METADATA
fast_safe_rl-0.1.0.dist-info/WHEEL
fast_safe_rl-0.1.0.dist-info/top_level.txt
fast_safe_rl-0.1.0.dist-info/RECORD
